webpack_bridge/__init__.py
webpack_bridge/apps.py
webpack_bridge/errors.py
webpack_bridge/manifest.py
webpack_bridge/settings.py
webpack_bridge/templatetags/__init__.py
webpack_bridge/templatetags/webpack_bridge.py
webpack_bridge/tests/__init__.py
webpack_bridge/tests/entrypoint_resolver.py
webpack_bridge/tests/tag_translater.py
webpack_bridge/tests/template_tags.py
webpack_bridge/tests/utils.py
webpack_bridge/tests/webpack_manifest.py
django_webpack_bridge-0.1.4.dist-info/WHEEL
django_webpack_bridge-0.1.4.dist-info/METADATA
django_webpack_bridge-0.1.4.dist-info/RECORD
