Metadata-Version: 2.1
Name: django-webpack-bridge
Version: 0.1.4
Summary: A bridge from Webpack to Django
Home-page: https://github.com/uw-it-aca/django-webpack-bridge
Keywords: django,webpack
Author: UW-IT AXDD
Author-email: aca-it@uw.edu
Requires-Python: >=3.6,<4.0
Classifier: Environment :: Web Environment
Classifier: Framework :: Django
Classifier: Framework :: Django :: 2.1
Classifier: Framework :: Django :: 2.2
Classifier: Framework :: Django :: 3.0
Classifier: Framework :: Django :: 3.1
Classifier: License :: OSI Approved :: Apache Software License
Classifier: Programming Language :: Python :: 3
Classifier: Programming Language :: Python :: 3 :: Only
Classifier: Programming Language :: Python :: 3.6
Classifier: Programming Language :: Python :: 3.7
Classifier: Programming Language :: Python :: 3.8
Classifier: Programming Language :: Python :: 3.9
Requires-Dist: Django (>=2.0.0)
Project-URL: Repository, https://github.com/uw-it-aca/django-webpack-bridge
